README.md
setup.cfg
setup.py
elastalert/__init__.py
elastalert/alerts.py
elastalert/auth.py
elastalert/config.py
elastalert/create_index.py
elastalert/elastalert.py
elastalert/enhancements.py
elastalert/kibana.py
elastalert/opsgenie.py
elastalert/rule_from_kibana.py
elastalert/ruletypes.py
elastalert/schema.yaml
elastalert/test_rule.py
elastalert/util.py
elastalert.egg-info/PKG-INFO
elastalert.egg-info/SOURCES.txt
elastalert.egg-info/dependency_links.txt
elastalert.egg-info/entry_points.txt
elastalert.egg-info/requires.txt
elastalert.egg-info/top_level.txt
tests/__init__.py
tests/alerts_test.py
tests/auth_test.py
tests/base_test.py
tests/config_test.py
tests/conftest.py
tests/kibana_test.py
tests/rules_test.py
tests/util_test.py