Metadata-Version: 1.1
Name: elastalert
Version: 0.1.30
Summary: Runs custom filters on Elasticsearch and alerts on matches
Home-page: UNKNOWN
Author: Quentin Long
Author-email: qlo@yelp.com
License: Copyright 2014 Yelp
Platform: UNKNOWN
Classifier: Programming Language :: Python :: 2.7
Classifier: License :: OSI Approved :: Apache Software License
Classifier: Operating System :: OS Independent
